[{"id":1,"student_name_surname":"Jared Philips","parent_name_surname":"Lamont Santon","address":"5 Sommers Center","telephone":"668-647-6041","email":"lsanton0@theguardian.com","group":12,"identification_number":"2895569509"},
{"id":2,"student_name_surname":"Darius Doughtery","parent_name_surname":"Nicol Trowell","address":"3 Florence Avenue","telephone":"637-959-4201","email":"ntrowell1@geocities.com","group":11,"identification_number":"6806354068"},
{"id":3,"student_name_surname":"Morganica Lilywhite","parent_name_surname":"Ikey Baudesson","address":"9 Goodland Center","telephone":"576-387-6947","email":"ibaudesson2@t-online.de","group":4,"identification_number":"6938538743"},
{"id":4,"student_name_surname":"Norina Staddon","parent_name_surname":"Stephannie Grigoliis","address":"87949 Graceland Plaza","telephone":"579-782-3543","email":"sgrigoliis3@liveinternet.ru","group":8,"identification_number":"9646251315"},
{"id":5,"student_name_surname":"Freeland Dandison","parent_name_surname":"Gardie Tollfree","address":"16822 Cambridge Point","telephone":"713-407-0197","email":"gtollfree4@ucla.edu","group":4,"identification_number":"7693975330"},
{"id":6,"student_name_surname":"Spense Stiffell","parent_name_surname":"Candie Sweetenham","address":"085 Rockefeller Road","telephone":"451-650-0708","email":"csweetenham5@tamu.edu","group":11,"identification_number":"4111030629"},
{"id":7,"student_name_surname":"Eudora Hawkslee","parent_name_surname":"Kory Delahunty","address":"43 Ridgeview Plaza","telephone":"509-941-3271","email":"kdelahunty6@fotki.com","group":5,"identification_number":"5315363732"},
{"id":8,"student_name_surname":"Celka Crathern","parent_name_surname":"Katrine Seppey","address":"3 Waywood Parkway","telephone":"944-493-4585","email":"kseppey7@businessweek.com","group":12,"identification_number":"6162038459"},
{"id":9,"student_name_surname":"Dehlia Janzen","parent_name_surname":"Trent Rheaume","address":"59 Daystar Crossing","telephone":"470-444-2424","email":"trheaume8@chron.com","group":7,"identification_number":"0926624903"},
{"id":10,"student_name_surname":"Zeb Degenhardt","parent_name_surname":"Barnabe Palfrey","address":"074 Almo Terrace","telephone":"341-691-6541","email":"bpalfrey9@prweb.com","group":7,"identification_number":"4460514591"},
{"id":11,"student_name_surname":"Mahalia Rofe","parent_name_surname":"Worthy Smurfitt","address":"4 Arrowood Avenue","telephone":"328-260-6759","email":"wsmurfitta@mediafire.com","group":11,"identification_number":"2390852947"},
{"id":12,"student_name_surname":"Forester Tanguy","parent_name_surname":"Letty Cowern","address":"65 Grim Crossing","telephone":"507-445-8128","email":"lcowernb@alexa.com","group":12,"identification_number":"1464226660"},
{"id":13,"student_name_surname":"Lillian Siddons","parent_name_surname":"Alene Towne","address":"25 Sauthoff Park","telephone":"980-851-7119","email":"atownec@ibm.com","group":1,"identification_number":"8639492158"},
{"id":14,"student_name_surname":"Brendis Debling","parent_name_surname":"Sydel Jeannon","address":"0513 Myrtle Lane","telephone":"871-935-7553","email":"sjeannond@flavors.me","group":3,"identification_number":"6697387041"},
{"id":15,"student_name_surname":"Violet Ringwood","parent_name_surname":"Ethelred Schruyers","address":"743 Village Avenue","telephone":"224-505-9297","email":"eschruyerse@multiply.com","group":11,"identification_number":"1954665865"},
{"id":16,"student_name_surname":"Kalina West-Frimley","parent_name_surname":"Anjela Sinderland","address":"84784 Fairfield Plaza","telephone":"619-841-0776","email":"asinderlandf@diigo.com","group":11,"identification_number":"3217235290"},
{"id":17,"student_name_surname":"Robbyn Stolte","parent_name_surname":"Prisca Nulty","address":"884 Washington Trail","telephone":"937-877-5082","email":"pnultyg@usda.gov","group":8,"identification_number":"5940169260"},
{"id":18,"student_name_surname":"Elyssa Pietrusiak","parent_name_surname":"Maritsa Yaus","address":"9365 Annamark Alley","telephone":"564-665-0562","email":"myaush@rambler.ru","group":10,"identification_number":"2694025269"},
{"id":19,"student_name_surname":"Frasier Yantsev","parent_name_surname":"Germaine Bril","address":"494 Daystar Parkway","telephone":"246-167-4750","email":"gbrili@mac.com","group":2,"identification_number":"6280758362"},
{"id":20,"student_name_surname":"Thorstein Corness","parent_name_surname":"Doll Hartil","address":"6 Schurz Place","telephone":"358-790-3236","email":"dhartilj@accuweather.com","group":4,"identification_number":"8786693638"},
{"id":21,"student_name_surname":"Benny Lintot","parent_name_surname":"Carolus Jankovsky","address":"968 Vahlen Lane","telephone":"219-264-4321","email":"cjankovskyk@accuweather.com","group":12,"identification_number":"9620942426"},
{"id":22,"student_name_surname":"Quillan Sheber","parent_name_surname":"Trudi Clear","address":"3682 Ohio Drive","telephone":"878-387-9388","email":"tclearl@sbwire.com","group":6,"identification_number":"7780632156"},
{"id":23,"student_name_surname":"Selie Swalwell","parent_name_surname":"Locke Shermore","address":"31 Warner Place","telephone":"621-482-7625","email":"lshermorem@npr.org","group":11,"identification_number":"5191943147"},
{"id":24,"student_name_surname":"Ransell Banstead","parent_name_surname":"Netta Eadmeades","address":"61399 Grim Plaza","telephone":"582-844-1978","email":"neadmeadesn@slate.com","group":7,"identification_number":"0818381787"},
{"id":25,"student_name_surname":"Herminia Husset","parent_name_surname":"Georas Chandler","address":"323 Express Way","telephone":"678-512-0372","email":"gchandlero@addtoany.com","group":9,"identification_number":"7142994177"},
{"id":26,"student_name_surname":"Howard Attenborough","parent_name_surname":"Riva Terbrug","address":"879 Dawn Center","telephone":"540-265-3281","email":"rterbrugp@csmonitor.com","group":4,"identification_number":"7362935323"},
{"id":27,"student_name_surname":"Cristie Lubomirski","parent_name_surname":"Wyndham Maps","address":"3324 Rusk Street","telephone":"805-941-8873","email":"wmapsq@qq.com","group":5,"identification_number":"1562061879"},
{"id":28,"student_name_surname":"Neddy Badland","parent_name_surname":"Crista Veart","address":"68965 Lakeland Parkway","telephone":"294-764-5777","email":"cveartr@rambler.ru","group":1,"identification_number":"4995377913"},
{"id":29,"student_name_surname":"Blinnie Zanni","parent_name_surname":"Chen Kohrs","address":"2 Hauk Plaza","telephone":"763-884-0133","email":"ckohrss@nifty.com","group":7,"identification_number":"5853202847"},
{"id":30,"student_name_surname":"Stephan Moffet","parent_name_surname":"Gwyneth Frearson","address":"9162 Everett Park","telephone":"117-831-1538","email":"gfrearsont@indiatimes.com","group":5,"identification_number":"0422154687"},
{"id":31,"student_name_surname":"Bengt Straker","parent_name_surname":"Emogene Gilfoy","address":"475 Starling Junction","telephone":"633-334-1458","email":"egilfoyu@bluehost.com","group":11,"identification_number":"4773300590"},
{"id":32,"student_name_surname":"Charlton Pooly","parent_name_surname":"Lainey Jakeman","address":"809 Towne Point","telephone":"235-452-3602","email":"ljakemanv@people.com.cn","group":7,"identification_number":"6829706467"},
{"id":33,"student_name_surname":"Lief Eschelle","parent_name_surname":"Kial Campling","address":"9 Birchwood Circle","telephone":"223-762-5801","email":"kcamplingw@studiopress.com","group":9,"identification_number":"9668952286"},
{"id":34,"student_name_surname":"Blinnie Doumic","parent_name_surname":"Kirbee Brimm","address":"33 Novick Avenue","telephone":"914-585-5246","email":"kbrimmx@prweb.com","group":12,"identification_number":"7446142006"},
{"id":35,"student_name_surname":"Ronny Sidgwick","parent_name_surname":"Brandtr Audenis","address":"279 Hanover Point","telephone":"658-693-3288","email":"baudenisy@slashdot.org","group":11,"identification_number":"0716646528"},
{"id":36,"student_name_surname":"Harley Levitt","parent_name_surname":"Honey Cripin","address":"334 Gateway Junction","telephone":"670-459-6072","email":"hcripinz@ftc.gov","group":12,"identification_number":"8551756761"},
{"id":37,"student_name_surname":"Ginevra Mogg","parent_name_surname":"Gris McGown","address":"5 Fuller Road","telephone":"856-767-9927","email":"gmcgown10@github.io","group":2,"identification_number":"4825422128"},
{"id":38,"student_name_surname":"Renard Campbell","parent_name_surname":"Siffre Jepensen","address":"1466 Golf Pass","telephone":"662-433-1152","email":"sjepensen11@multiply.com","group":1,"identification_number":"0197782477"},
{"id":39,"student_name_surname":"Bernelle Milsted","parent_name_surname":"Gael Iwanowicz","address":"60989 School Avenue","telephone":"127-158-3830","email":"giwanowicz12@wisc.edu","group":5,"identification_number":"9381141606"},
{"id":40,"student_name_surname":"Jean Scourge","parent_name_surname":"Mariam Hamnet","address":"60355 Moose Drive","telephone":"881-972-9999","email":"mhamnet13@nsw.gov.au","group":8,"identification_number":"2741178410"},
{"id":41,"student_name_surname":"Richart Allward","parent_name_surname":"Morgun Aveyard","address":"65 Shasta Place","telephone":"704-824-8595","email":"maveyard14@mtv.com","group":6,"identification_number":"8320252938"},
{"id":42,"student_name_surname":"Malina Abelson","parent_name_surname":"Olivia Wainwright","address":"0113 Mcguire Alley","telephone":"570-836-4495","email":"owainwright15@bandcamp.com","group":3,"identification_number":"8999619141"},
{"id":43,"student_name_surname":"Silvia Long","parent_name_surname":"Dorey Laugharne","address":"76586 Montana Avenue","telephone":"989-786-1495","email":"dlaugharne16@elpais.com","group":5,"identification_number":"1910106194"},
{"id":44,"student_name_surname":"Lowell Brameld","parent_name_surname":"Kerri Jerrim","address":"762 Mayfield Road","telephone":"655-660-9033","email":"kjerrim17@indiegogo.com","group":1,"identification_number":"2496909144"},
{"id":45,"student_name_surname":"Sal Lamp","parent_name_surname":"Christy Lapides","address":"825 Kings Terrace","telephone":"473-234-6162","email":"clapides18@pagesperso-orange.fr","group":9,"identification_number":"0772165831"},
{"id":46,"student_name_surname":"Cullin Kleinsmuntz","parent_name_surname":"Anselm Minthorpe","address":"2 Pawling Circle","telephone":"836-115-4461","email":"aminthorpe19@last.fm","group":12,"identification_number":"9178237211"},
{"id":47,"student_name_surname":"Hakeem Skellon","parent_name_surname":"Aldon Whitlock","address":"05207 Longview Circle","telephone":"750-833-0183","email":"awhitlock1a@telegraph.co.uk","group":5,"identification_number":"5829791315"},
{"id":48,"student_name_surname":"Lee Chattaway","parent_name_surname":"Alexandro Reed","address":"53477 Memorial Parkway","telephone":"445-514-1368","email":"areed1b@gmpg.org","group":4,"identification_number":"0652208754"},
{"id":49,"student_name_surname":"Leann Berrecloth","parent_name_surname":"Christos Riden","address":"7582 Pleasure Park","telephone":"307-363-8464","email":"criden1c@istockphoto.com","group":7,"identification_number":"8402839592"},
{"id":50,"student_name_surname":"Isidro Cosh","parent_name_surname":"Dode Schlagtmans","address":"863 Eagan Trail","telephone":"106-779-2151","email":"dschlagtmans1d@shinystat.com","group":8,"identification_number":"0957493207"}]